{
"type": "FeatureCollection",
                                                                                
"features": [
{ "type": "Feature", "properties": { "RailFltyId": "CA000003", "Tract": "06013316000", "Longitude": -122.136353, "Latitude": 38.019733, "stype": null, "lqfsuscat": 5, "lndsuscat": 0, "w_depth": 0.0, "pgv": 16.0, "pga": 0.24, "sa03": 0.52, "sa10": 0.28, "LqfSettlPG": 0.0, "LqfSprPGD": 0.0, "LqfProb": 0.0, "LndPGD": 0.0, "LndProb": 0.0, "SufFltRupt": 0.0, "SurfFltRup": 0.0, "CountyName": "Contra Costa", "RailFlty_1": "CA000003", "TranspFclt": "RDFLT", "eqBldgType": "DFLT", "Tract_1": "06013316000", "Name": "Martinez, California", "Address": "601 Marina Vista Ave.", "City": "Martinez", "Zipcode": "94553-1132", "Statea": "CA", "FunctDay1": 80.9, "FunctDay3": 88.6, "FunctDay7": 91.3, "FunctDay14": 91.6, "FunctDay30": 92.3, "FunctDay90": 95.3, "PDsNone": 0.1012, "PDsSlight": 0.6342, "PDsModerat": 0.1626, "PDsExtensi": 0.0501, "PDsComplet": 0.0516, "PDsExceedS": 0.8987, "PDsExceedM": 0.2644, "PDsExceedE": 0.1018, "Latitude_1": 38.019733, "Longitude_": -122.136353, "CountyFips": "06013" }, "geometry": { "type": "Point", "coordinates": [ -122.136349999998856, 38.01973 ] } },
{ "type": "Feature", "properties": { "RailFltyId": "CA000008", "Tract": "06047001302", "Longitude": -120.475891, "Latitude": 37.307041, "stype": null, "lqfsuscat": 0, "lndsuscat": 0, "w_depth": 0.0, "pgv": 4.0, "pga": 0.04, "sa03": 0.12, "sa10": 0.08, "LqfSettlPG": 0.0, "LqfSprPGD": 0.0, "LqfProb": 0.0, "LndPGD": 0.0, "LndProb": 0.0, "SufFltRupt": 0.0, "SurfFltRup": 0.0, "CountyName": "Merced", "RailFlty_1": "CA000008", "TranspFclt": "RDFLT", "eqBldgType": "DFLT", "Tract_1": "06047001302", "Name": "Merced, California", "Address": "324 West 24th St", "City": "Merced", "Zipcode": "95340", "Statea": "CA", "FunctDay1": 99.9, "FunctDay3": 99.9, "FunctDay7": 99.9, "FunctDay14": 99.9, "FunctDay30": 99.9, "FunctDay90": 99.9, "PDsNone": 0.9046, "PDsSlight": 0.0947, "PDsModerat": 0.0006, "PDsExtensi": 0.0, "PDsComplet": 0.0, "PDsExceedS": 0.0953, "PDsExceedM": 0.0006, "PDsExceedE": 0.0, "Latitude_1": 37.307041, "Longitude_": -120.475891, "CountyFips": "06047" }, "geometry": { "type": "Point", "coordinates": [ -120.475889999999708, 37.307040000001507 ] } },
{ "type": "Feature", "properties": { "RailFltyId": "CA000013", "Tract": "06001436300", "Longitude": -122.097786, "Latitude": 37.666859, "stype": null, "lqfsuscat": 3, "lndsuscat": 0, "w_depth": 0.0, "pgv": 36.0, "pga": 0.6, "sa03": 1.32, "sa10": 0.76, "LqfSettlPG": 0.0, "LqfSprPGD": 0.0, "LqfProb": 0.0, "LndPGD": 0.0, "LndProb": 0.0, "SufFltRupt": 0.0, "SurfFltRup": 0.0, "CountyName": "Alameda", "RailFlty_1": "CA000013", "TranspFclt": "RDFLT", "eqBldgType": "DFLT", "Tract_1": "06001436300", "Name": "Hayward, California", "Address": "22555 Meekland Avenue", "City": "Hayward", "Zipcode": "94541", "Statea": "CA", "FunctDay1": 43.2, "FunctDay3": 57.1, "FunctDay7": 62.3, "FunctDay14": 63.5, "FunctDay30": 66.7, "FunctDay90": 80.4, "PDsNone": 0.005, "PDsSlight": 0.2597, "PDsModerat": 0.2879, "PDsExtensi": 0.237, "PDsComplet": 0.2101, "PDsExceedS": 0.9949, "PDsExceedM": 0.7351, "PDsExceedE": 0.4472, "Latitude_1": 37.666859, "Longitude_": -122.097786, "CountyFips": "06001" }, "geometry": { "type": "Point", "coordinates": [ -122.097789999999804, 37.666860000001179 ] } },
{ "type": "Feature", "properties": { "RailFltyId": "CA000018", "Tract": "06001422000", "Longitude": -122.299995, "Latitude": 37.867603, "stype": null, "lqfsuscat": 2, "lndsuscat": 0, "w_depth": 0.0, "pgv": 24.0, "pga": 0.32, "sa03": 0.68, "sa10": 0.52, "LqfSettlPG": 0.0, "LqfSprPGD": 0.0, "LqfProb": 0.0, "LndPGD": 0.0, "LndProb": 0.0, "SufFltRupt": 0.0, "SurfFltRup": 0.0, "CountyName": "Alameda", "RailFlty_1": "CA000018", "TranspFclt": "RDFLT", "eqBldgType": "DFLT", "Tract_1": "06001422000", "Name": "Berkeley, California", "Address": "University Ave. and Third St.", "City": "Berkeley", "Zipcode": "94710", "Statea": "CA", "FunctDay1": 73.4, "FunctDay3": 85.0, "FunctDay7": 89.0, "FunctDay14": 89.5, "FunctDay30": 90.7, "FunctDay90": 95.7, "PDsNone": 0.0483, "PDsSlight": 0.5763, "PDsModerat": 0.243, "PDsExtensi": 0.1021, "PDsComplet": 0.03, "PDsExceedS": 0.9516, "PDsExceedM": 0.3752, "PDsExceedE": 0.1322, "Latitude_1": 37.867603, "Longitude_": -122.299995, "CountyFips": "06001" }, "geometry": { "type": "Point", "coordinates": [ -122.299989999999525, 37.867600000001403 ] } },
{ "type": "Feature", "properties": { "RailFltyId": "CA000021", "Tract": "06001425100", "Longitude": -122.29068, "Latitude": 37.840679, "stype": null, "lqfsuscat": 4, "lndsuscat": 0, "w_depth": 0.0, "pgv": 20.0, "pga": 0.32, "sa03": 0.64, "sa10": 0.48, "LqfSettlPG": 0.0, "LqfSprPGD": 0.0, "LqfProb": 0.0, "LndPGD": 0.0, "LndProb": 0.0, "SufFltRupt": 0.0, "SurfFltRup": 0.0, "CountyName": "Alameda", "RailFlty_1": "CA000021", "TranspFclt": "RDFLT", "eqBldgType": "DFLT", "Tract_1": "06001425100", "Name": "Emeryville, California", "Address": "5885 Horton Street", "City": "Emeryville", "Zipcode": "94608-2037", "Statea": "CA", "FunctDay1": 71.3, "FunctDay3": 82.6, "FunctDay7": 86.5, "FunctDay14": 87.0, "FunctDay30": 88.3, "FunctDay90": 93.6, "PDsNone": 0.0467, "PDsSlight": 0.5576, "PDsModerat": 0.2351, "PDsExtensi": 0.0988, "PDsComplet": 0.0616, "PDsExceedS": 0.9532, "PDsExceedM": 0.3955, "PDsExceedE": 0.1604, "Latitude_1": 37.840679, "Longitude_": -122.29068, "CountyFips": "06001" }, "geometry": { "type": "Point", "coordinates": [ -122.29068, 37.840680000001157 ] } },
{ "type": "Feature", "properties": { "RailFltyId": "CA000024", "Tract": "06095252702", "Longitude": -122.039543, "Latitude": 38.243465, "stype": null, "lqfsuscat": 5, "lndsuscat": 0, "w_depth": 0.0, "pgv": 4.0, "pga": 0.12, "sa03": 0.36, "sa10": 0.12, "LqfSettlPG": 0.0, "LqfSprPGD": 0.0, "LqfProb": 0.0, "LndPGD": 0.0, "LndProb": 0.0, "SufFltRupt": 0.0, "SurfFltRup": 0.0, "CountyName": "Solano", "RailFlty_1": "CA000024", "TranspFclt": "RDFLT", "eqBldgType": "DFLT", "Tract_1": "06095252702", "Name": "Suisun, California", "Address": "177 Main Street", "City": "Suisun", "Zipcode": "94585", "Statea": "CA", "FunctDay1": 97.1, "FunctDay3": 98.8, "FunctDay7": 99.4, "FunctDay14": 99.4, "FunctDay30": 99.5, "FunctDay90": 99.7, "PDsNone": 0.3971, "PDsSlight": 0.5596, "PDsModerat": 0.0368, "PDsExtensi": 0.0053, "PDsComplet": 0.001, "PDsExceedS": 0.6028, "PDsExceedM": 0.0432, "PDsExceedE": 0.0063, "Latitude_1": 38.243465, "Longitude_": -122.039543, "CountyFips": "06095" }, "geometry": { "type": "Point", "coordinates": [ -122.039539999999761, 38.243470000001253 ] } },
{ "type": "Feature", "properties": { "RailFltyId": "CA000026", "Tract": "06067005300", "Longitude": -121.49955, "Latitude": 38.58403, "stype": null, "lqfsuscat": 0, "lndsuscat": 0, "w_depth": 0.0, "pgv": 2.0, "pga": 0.08, "sa03": 0.16, "sa10": 0.04, "LqfSettlPG": 0.0, "LqfSprPGD": 0.0, "LqfProb": 0.0, "LndPGD": 0.0, "LndProb": 0.0, "SufFltRupt": 0.0, "SurfFltRup": 0.0, "CountyName": "Sacramento", "RailFlty_1": "CA000026", "TranspFclt": "RDFLT", "eqBldgType": "DFLT", "Tract_1": "06067005300", "Name": "Sacramento, California", "Address": "401 I Street", "City": "Sacramento", "Zipcode": "95814-2308", "Statea": "CA", "FunctDay1": 99.2, "FunctDay3": 99.7, "FunctDay7": 99.8, "FunctDay14": 99.9, "FunctDay30": 99.9, "FunctDay90": 99.9, "PDsNone": 0.625, "PDsSlight": 0.3641, "PDsModerat": 0.0097, "PDsExtensi": 0.0009, "PDsComplet": 0.0001, "PDsExceedS": 0.3749, "PDsExceedM": 0.0108, "PDsExceedE": 0.001, "Latitude_1": 38.58403, "Longitude_": -121.49955, "CountyFips": "06067" }, "geometry": { "type": "Point", "coordinates": [ -121.499549999998635, 38.58403 ] } },
{ "type": "Feature", "properties": { "RailFltyId": "CA000029", "Tract": "06099003604", "Longitude": -120.798798, "Latitude": 37.530312, "stype": null, "lqfsuscat": 0, "lndsuscat": 0, "w_depth": 0.0, "pgv": 4.0, "pga": 0.08, "sa03": 0.16, "sa10": 0.08, "LqfSettlPG": 0.0, "LqfSprPGD": 0.0, "LqfProb": 0.0, "LndPGD": 0.0, "LndProb": 0.0, "SufFltRupt": 0.0, "SurfFltRup": 0.0, "CountyName": "Stanislaus", "RailFlty_1": "CA000029", "TranspFclt": "RDFLT", "eqBldgType": "DFLT", "Tract_1": "06099003604", "Name": "Turlock-Denair, California", "Address": "3800 Santa Fe Avenue", "City": "Denair", "Zipcode": "95316", "Statea": "CA", "FunctDay1": 99.2, "FunctDay3": 99.7, "FunctDay7": 99.8, "FunctDay14": 99.9, "FunctDay30": 99.9, "FunctDay90": 99.9, "PDsNone": 0.625, "PDsSlight": 0.3641, "PDsModerat": 0.0097, "PDsExtensi": 0.0009, "PDsComplet": 0.0001, "PDsExceedS": 0.3749, "PDsExceedM": 0.0108, "PDsExceedE": 0.001, "Latitude_1": 37.530312, "Longitude_": -120.798798, "CountyFips": "06099" }, "geometry": { "type": "Point", "coordinates": [ -120.798799999998664, 37.5303100000001 ] } },
{ "type": "Feature", "properties": { "RailFltyId": "CA000034", "Tract": "06077000100", "Longitude": -121.278989, "Latitude": 37.956668, "stype": null, "lqfsuscat": 0, "lndsuscat": 0, "w_depth": 0.0, "pgv": 4.0, "pga": 0.12, "sa03": 0.32, "sa10": 0.12, "LqfSettlPG": 0.0, "LqfSprPGD": 0.0, "LqfProb": 0.0, "LndPGD": 0.0, "LndProb": 0.0, "SufFltRupt": 0.0, "SurfFltRup": 0.0, "CountyName": "San Joaquin", "RailFlty_1": "CA000034", "TranspFclt": "RDFLT", "eqBldgType": "DFLT", "Tract_1": "06077000100", "Name": "Stockton (ACE, 701-704), California", "Address": "949 East Channel St.", "City": "Stockton", "Zipcode": "95202", "Statea": "CA", "FunctDay1": 97.1, "FunctDay3": 98.9, "FunctDay7": 99.4, "FunctDay14": 99.5, "FunctDay30": 99.5, "FunctDay90": 99.8, "PDsNone": 0.3972, "PDsSlight": 0.5599, "PDsModerat": 0.0368, "PDsExtensi": 0.0053, "PDsComplet": 0.0006, "PDsExceedS": 0.6027, "PDsExceedM": 0.0428, "PDsExceedE": 0.0059, "Latitude_1": 37.956668, "Longitude_": -121.278989, "CountyFips": "06077" }, "geometry": { "type": "Point", "coordinates": [ -121.278989999998885, 37.956670000001395 ] } },
{ "type": "Feature", "properties": { "RailFltyId": "CA000035", "Tract": "06077000700", "Longitude": -121.284271, "Latitude": 37.946011, "stype": null, "lqfsuscat": 0, "lndsuscat": 0, "w_depth": 0.0, "pgv": 4.0, "pga": 0.12, "sa03": 0.32, "sa10": 0.12, "LqfSettlPG": 0.0, "LqfSprPGD": 0.0, "LqfProb": 0.0, "LndPGD": 0.0, "LndProb": 0.0, "SufFltRupt": 0.0, "SurfFltRup": 0.0, "CountyName": "San Joaquin", "RailFlty_1": "CA000035", "TranspFclt": "RDFLT", "eqBldgType": "DFLT", "Tract_1": "06077000700", "Name": "Stockton (711-718), California", "Address": "735 S. San Joaquin St", "City": "Stockton", "Zipcode": "95203", "Statea": "CA", "FunctDay1": 97.1, "FunctDay3": 98.9, "FunctDay7": 99.4, "FunctDay14": 99.5, "FunctDay30": 99.5, "FunctDay90": 99.8, "PDsNone": 0.3972, "PDsSlight": 0.5599, "PDsModerat": 0.0368, "PDsExtensi": 0.0053, "PDsComplet": 0.0006, "PDsExceedS": 0.6027, "PDsExceedM": 0.0428, "PDsExceedE": 0.0059, "Latitude_1": 37.946011, "Longitude_": -121.284271, "CountyFips": "06077" }, "geometry": { "type": "Point", "coordinates": [ -121.284269999998287, 37.946010000001479 ] } },
{ "type": "Feature", "properties": { "RailFltyId": "CA000046", "Tract": "06013305000", "Longitude": -121.815132, "Latitude": 38.018085, "stype": null, "lqfsuscat": 4, "lndsuscat": 0, "w_depth": 0.0, "pgv": 8.0, "pga": 0.2, "sa03": 0.44, "sa10": 0.2, "LqfSettlPG": 0.0, "LqfSprPGD": 0.0, "LqfProb": 0.0, "LndPGD": 0.0, "LndProb": 0.0, "SufFltRupt": 0.0, "SurfFltRup": 0.0, "CountyName": "Contra Costa", "RailFlty_1": "CA000046", "TranspFclt": "RDFLT", "eqBldgType": "DFLT", "Tract_1": "06013305000", "Name": "Antioch-Pittsburg, California", "Address": "100 I Street", "City": "Antioch", "Zipcode": "94509-1122", "Statea": "CA", "FunctDay1": 88.7, "FunctDay3": 94.6, "FunctDay7": 96.6, "FunctDay14": 96.8, "FunctDay30": 97.2, "FunctDay90": 98.7, "PDsNone": 0.1605, "PDsSlight": 0.6756, "PDsModerat": 0.1238, "PDsExtensi": 0.0314, "PDsComplet": 0.0084, "PDsExceedS": 0.8394, "PDsExceedM": 0.1637, "PDsExceedE": 0.0398, "Latitude_1": 38.018085, "Longitude_": -121.815132, "CountyFips": "06013" }, "geometry": { "type": "Point", "coordinates": [ -121.815129999999044, 38.018090000001393 ] } },
{ "type": "Feature", "properties": { "RailFltyId": "CA000047", "Tract": "06099002803", "Longitude": -120.911598, "Latitude": 37.66814, "stype": null, "lqfsuscat": 0, "lndsuscat": 0, "w_depth": 0.0, "pgv": 4.0, "pga": 0.08, "sa03": 0.16, "sa10": 0.08, "LqfSettlPG": 0.0, "LqfSprPGD": 0.0, "LqfProb": 0.0, "LndPGD": 0.0, "LndProb": 0.0, "SufFltRupt": 0.0, "SurfFltRup": 0.0, "CountyName": "Stanislaus", "RailFlty_1": "CA000047", "TranspFclt": "RDFLT", "eqBldgType": "DFLT", "Tract_1": "06099002803", "Name": "Modesto, California", "Address": "1700 Held Drive", "City": "Modesto", "Zipcode": "95355-8301", "Statea": "CA", "FunctDay1": 99.2, "FunctDay3": 99.7, "FunctDay7": 99.8, "FunctDay14": 99.9, "FunctDay30": 99.9, "FunctDay90": 99.9, "PDsNone": 0.625, "PDsSlight": 0.3641, "PDsModerat": 0.0097, "PDsExtensi": 0.0009, "PDsComplet": 0.0001, "PDsExceedS": 0.3749, "PDsExceedM": 0.0108, "PDsExceedE": 0.001, "Latitude_1": 37.66814, "Longitude_": -120.911598, "CountyFips": "06099" }, "geometry": { "type": "Point", "coordinates": [ -120.911599999999453, 37.668140000001586 ] } },
{ "type": "Feature", "properties": { "RailFltyId": "CA000048", "Tract": "06113010602", "Longitude": -121.737068, "Latitude": 38.544113, "stype": null, "lqfsuscat": 0, "lndsuscat": 0, "w_depth": 0.0, "pgv": 4.0, "pga": 0.08, "sa03": 0.2, "sa10": 0.08, "LqfSettlPG": 0.0, "LqfSprPGD": 0.0, "LqfProb": 0.0, "LndPGD": 0.0, "LndProb": 0.0, "SufFltRupt": 0.0, "SurfFltRup": 0.0, "CountyName": "Yolo", "RailFlty_1": "CA000048", "TranspFclt": "RDFLT", "eqBldgType": "DFLT", "Tract_1": "06113010602", "Name": "Davis, California", "Address": "840 Second Street", "City": "Davis", "Zipcode": "95616-4624", "Statea": "CA", "FunctDay1": 99.2, "FunctDay3": 99.7, "FunctDay7": 99.8, "FunctDay14": 99.9, "FunctDay30": 99.9, "FunctDay90": 99.9, "PDsNone": 0.625, "PDsSlight": 0.3641, "PDsModerat": 0.0097, "PDsExtensi": 0.0009, "PDsComplet": 0.0001, "PDsExceedS": 0.3749, "PDsExceedM": 0.0108, "PDsExceedE": 0.001, "Latitude_1": 38.544113, "Longitude_": -121.737068, "CountyFips": "06113" }, "geometry": { "type": "Point", "coordinates": [ -121.737069999999221, 38.544110000000728 ] } },
{ "type": "Feature", "properties": { "RailFltyId": "CA000050", "Tract": "06077004204", "Longitude": -121.271594, "Latitude": 38.13354, "stype": null, "lqfsuscat": 0, "lndsuscat": 0, "w_depth": 0.0, "pgv": 4.0, "pga": 0.12, "sa03": 0.24, "sa10": 0.08, "LqfSettlPG": 0.0, "LqfSprPGD": 0.0, "LqfProb": 0.0, "LndPGD": 0.0, "LndProb": 0.0, "SufFltRupt": 0.0, "SurfFltRup": 0.0, "CountyName": "San Joaquin", "RailFlty_1": "CA000050", "TranspFclt": "RDFLT", "eqBldgType": "DFLT", "Tract_1": "06077004204", "Name": "Lodi, California", "Address": "24 South Sacramento Street", "City": "Lodi", "Zipcode": "95240", "Statea": "CA", "FunctDay1": 97.1, "FunctDay3": 98.9, "FunctDay7": 99.4, "FunctDay14": 99.5, "FunctDay30": 99.5, "FunctDay90": 99.8, "PDsNone": 0.3972, "PDsSlight": 0.5599, "PDsModerat": 0.0368, "PDsExtensi": 0.0053, "PDsComplet": 0.0006, "PDsExceedS": 0.6027, "PDsExceedM": 0.0428, "PDsExceedE": 0.0059, "Latitude_1": 38.13354, "Longitude_": -121.271594, "CountyFips": "06077" }, "geometry": { "type": "Point", "coordinates": [ -121.271589999998469, 38.133540000000721 ] } },
{ "type": "Feature", "properties": { "RailFltyId": "CA000063", "Tract": "06001403300", "Longitude": -122.270744, "Latitude": 37.794647, "stype": null, "lqfsuscat": 3, "lndsuscat": 0, "w_depth": 0.0, "pgv": 20.0, "pga": 0.32, "sa03": 0.76, "sa10": 0.56, "LqfSettlPG": 0.0, "LqfSprPGD": 0.0, "LqfProb": 0.0, "LndPGD": 0.0, "LndProb": 0.0, "SufFltRupt": 0.0, "SurfFltRup": 0.0, "CountyName": "Alameda", "RailFlty_1": "CA000063", "TranspFclt": "RDFLT", "eqBldgType": "DFLT", "Tract_1": "06001403300", "Name": "Oakland, California", "Address": "245 Second Street", "City": "Oakland", "Zipcode": "94607", "Statea": "CA", "FunctDay1": 72.9, "FunctDay3": 84.4, "FunctDay7": 88.5, "FunctDay14": 88.9, "FunctDay30": 90.1, "FunctDay90": 95.2, "PDsNone": 0.0479, "PDsSlight": 0.572, "PDsModerat": 0.2412, "PDsExtensi": 0.1013, "PDsComplet": 0.0373, "PDsExceedS": 0.952, "PDsExceedM": 0.3799, "PDsExceedE": 0.1387, "Latitude_1": 37.794647, "Longitude_": -122.270744, "CountyFips": "06001" }, "geometry": { "type": "Point", "coordinates": [ -122.27074, 37.794650000001639 ] } },
{ "type": "Feature", "properties": { "RailFltyId": "CA000064", "Tract": "06001408800", "Longitude": -122.197740496, "Latitude": 37.751881255900003, "stype": null, "lqfsuscat": 5, "lndsuscat": 0, "w_depth": 0.0, "pgv": 40.0, "pga": 0.52, "sa03": 0.96, "sa10": 0.88, "LqfSettlPG": 0.0, "LqfSprPGD": 0.0, "LqfProb": 0.0, "LndPGD": 0.0, "LndProb": 0.0, "SufFltRupt": 0.0, "SurfFltRup": 0.0, "CountyName": "Alameda", "RailFlty_1": "CA000064", "TranspFclt": "RDFLT", "eqBldgType": "DFLT", "Tract_1": "06001408800", "Name": "Coliseum\/Oakland Airport, Oakland, Calif", "Address": "700 73rd Avenue", "City": "Oakland", "Zipcode": "94621-3316", "Statea": "CA", "FunctDay1": 45.6, "FunctDay3": 58.4, "FunctDay7": 63.2, "FunctDay14": 64.2, "FunctDay30": 67.0, "FunctDay90": 79.0, "PDsNone": 0.0079, "PDsSlight": 0.2941, "PDsModerat": 0.265, "PDsExtensi": 0.1873, "PDsComplet": 0.2454, "PDsExceedS": 0.992, "PDsExceedM": 0.6978, "PDsExceedE": 0.4327, "Latitude_1": 37.751881, "Longitude_": -122.19774, "CountyFips": "06001" }, "geometry": { "type": "Point", "coordinates": [ -122.197739999999612, 37.75188000000162 ] } },
{ "type": "Feature", "properties": { "RailFltyId": "CA000071", "Tract": "06085500300", "Longitude": -121.901207, "Latitude": 37.33107, "stype": null, "lqfsuscat": 3, "lndsuscat": 0, "w_depth": 0.0, "pgv": 20.0, "pga": 0.28, "sa03": 0.52, "sa10": 0.36, "LqfSettlPG": 0.0, "LqfSprPGD": 0.0, "LqfProb": 0.0, "LndPGD": 0.0, "LndProb": 0.0, "SufFltRupt": 0.0, "SurfFltRup": 0.0, "CountyName": "Santa Clara", "RailFlty_1": "CA000071", "TranspFclt": "RDFLT", "eqBldgType": "DFLT", "Tract_1": "06085500300", "Name": "San Jose, California", "Address": "65 Cahill Street", "City": "San Jose", "Zipcode": "95110", "Statea": "CA", "FunctDay1": 78.4, "FunctDay3": 88.3, "FunctDay7": 91.8, "FunctDay14": 92.2, "FunctDay30": 93.0, "FunctDay90": 96.8, "PDsNone": 0.0704, "PDsSlight": 0.6217, "PDsModerat": 0.2091, "PDsExtensi": 0.0761, "PDsComplet": 0.0224, "PDsExceedS": 0.9295, "PDsExceedM": 0.3077, "PDsExceedE": 0.0986, "Latitude_1": 37.33107, "Longitude_": -121.901207, "CountyFips": "06085" }, "geometry": { "type": "Point", "coordinates": [ -121.90121, 37.331070000000182 ] } },
{ "type": "Feature", "properties": { "RailFltyId": "CA000073", "Tract": "06001401700", "Longitude": -122.31121, "Latitude": 37.82307, "stype": null, "lqfsuscat": 5, "lndsuscat": 0, "w_depth": 0.0, "pgv": 20.0, "pga": 0.28, "sa03": 0.64, "sa10": 0.44, "LqfSettlPG": 0.0, "LqfSprPGD": 0.0, "LqfProb": 0.0, "LndPGD": 0.0, "LndProb": 0.0, "SufFltRupt": 0.0, "SurfFltRup": 0.0, "CountyName": "Alameda", "RailFlty_1": "CA000073", "TranspFclt": "RDFLT", "eqBldgType": "DFLT", "Tract_1": "06001401700", "Name": "UP-OAKLAND-CA-200 BURMA", "Address": null, "City": "OAKLAND", "Zipcode": "94607", "Statea": "CA", "FunctDay1": 73.9, "FunctDay3": 83.3, "FunctDay7": 86.6, "FunctDay14": 87.0, "FunctDay30": 88.0, "FunctDay90": 92.4, "PDsNone": 0.0658, "PDsSlight": 0.581, "PDsModerat": 0.1954, "PDsExtensi": 0.0711, "PDsComplet": 0.0864, "PDsExceedS": 0.9341, "PDsExceedM": 0.353, "PDsExceedE": 0.1576, "Latitude_1": 37.82307, "Longitude_": -122.31121, "CountyFips": "06001" }, "geometry": { "type": "Point", "coordinates": [ -122.311209999999846, 37.823070000000371 ] } },
{ "type": "Feature", "properties": { "RailFltyId": "CA000081", "Tract": "06001401900", "Longitude": -122.31917, "Latitude": 37.80946, "stype": null, "lqfsuscat": 5, "lndsuscat": 0, "w_depth": 0.0, "pgv": 20.0, "pga": 0.28, "sa03": 0.6, "sa10": 0.44, "LqfSettlPG": 0.0, "LqfSprPGD": 0.0, "LqfProb": 0.0, "LndPGD": 0.0, "LndProb": 0.0, "SufFltRupt": 0.0, "SurfFltRup": 0.0, "CountyName": "Alameda", "RailFlty_1": "CA000081", "TranspFclt": "RDFLT", "eqBldgType": "DFLT", "Tract_1": "06001401900", "Name": "UP-OAKLAND-CA-707 FERRY", "Address": null, "City": "OAKLAND", "Zipcode": "94607", "Statea": "CA", "FunctDay1": 73.9, "FunctDay3": 83.3, "FunctDay7": 86.6, "FunctDay14": 87.0, "FunctDay30": 88.0, "FunctDay90": 92.4, "PDsNone": 0.0658, "PDsSlight": 0.581, "PDsModerat": 0.1954, "PDsExtensi": 0.0711, "PDsComplet": 0.0864, "PDsExceedS": 0.9341, "PDsExceedM": 0.353, "PDsExceedE": 0.1576, "Latitude_1": 37.80946, "Longitude_": -122.31917, "CountyFips": "06001" }, "geometry": { "type": "Point", "coordinates": [ -122.319169999998849, 37.809460000000399 ] } },
{ "type": "Feature", "properties": { "RailFltyId": "CA000082", "Tract": "06001401900", "Longitude": -122.30774, "Latitude": 37.80172, "stype": null, "lqfsuscat": 5, "lndsuscat": 0, "w_depth": 0.0, "pgv": 24.0, "pga": 0.32, "sa03": 0.64, "sa10": 0.56, "LqfSettlPG": 0.0, "LqfSprPGD": 0.0, "LqfProb": 0.0, "LndPGD": 0.0, "LndProb": 0.0, "SufFltRupt": 0.0, "SurfFltRup": 0.0, "CountyName": "Alameda", "RailFlty_1": "CA000082", "TranspFclt": "RDFLT", "eqBldgType": "DFLT", "Tract_1": "06001401900", "Name": "UP-OAKLAND-CA-1776 MIDDL", "Address": null, "City": "OAKLAND", "Zipcode": "94607", "Statea": "CA", "FunctDay1": 66.2, "FunctDay3": 76.4, "FunctDay7": 80.1, "FunctDay14": 80.7, "FunctDay30": 82.1, "FunctDay90": 88.2, "PDsNone": 0.0427, "PDsSlight": 0.51, "PDsModerat": 0.215, "PDsExtensi": 0.0904, "PDsComplet": 0.1416, "PDsExceedS": 0.9572, "PDsExceedM": 0.4471, "PDsExceedE": 0.232, "Latitude_1": 37.80172, "Longitude_": -122.30774, "CountyFips": "06001" }, "geometry": { "type": "Point", "coordinates": [ -122.307739999998375, 37.801720000001296 ] } },
{ "type": "Feature", "properties": { "RailFltyId": "CA000083", "Tract": "06001409400", "Longitude": -122.18292, "Latitude": 37.74179, "stype": null, "lqfsuscat": 4, "lndsuscat": 0, "w_depth": 0.0, "pgv": 44.0, "pga": 0.6, "sa03": 1.08, "sa10": 1.28, "LqfSettlPG": 0.0, "LqfSprPGD": 0.0, "LqfProb": 0.0, "LndPGD": 0.0, "LndProb": 0.0, "SufFltRupt": 0.0, "SurfFltRup": 0.0, "CountyName": "Alameda", "RailFlty_1": "CA000083", "TranspFclt": "RDFLT", "eqBldgType": "DFLT", "Tract_1": "06001409400", "Name": "PACIFIC AMERICAN SERVICES-OAKLAND-CA", "Address": null, "City": "OAKLAND", "Zipcode": "94603", "Statea": "CA", "FunctDay1": 41.2, "FunctDay3": 54.2, "FunctDay7": 59.1, "FunctDay14": 60.4, "FunctDay30": 63.6, "FunctDay90": 77.3, "PDsNone": 0.0047, "PDsSlight": 0.2436, "PDsModerat": 0.27, "PDsExtensi": 0.2223, "PDsComplet": 0.2592, "PDsExceedS": 0.9952, "PDsExceedM": 0.7516, "PDsExceedE": 0.4815, "Latitude_1": 37.74179, "Longitude_": -122.18292, "CountyFips": "06001" }, "geometry": { "type": "Point", "coordinates": [ -122.182919999999285, 37.74179 ] } },
{ "type": "Feature", "properties": { "RailFltyId": "CA000084", "Tract": "06113010201", "Longitude": -121.5164, "Latitude": 38.58101, "stype": null, "lqfsuscat": 0, "lndsuscat": 0, "w_depth": 0.0, "pgv": 2.0, "pga": 0.08, "sa03": 0.16, "sa10": 0.04, "LqfSettlPG": 0.0, "LqfSprPGD": 0.0, "LqfProb": 0.0, "LndPGD": 0.0, "LndProb": 0.0, "SufFltRupt": 0.0, "SurfFltRup": 0.0, "CountyName": "Yolo", "RailFlty_1": "CA000084", "TranspFclt": "RDFLT", "eqBldgType": "DFLT", "Tract_1": "06113010201", "Name": "BNSF-SACRAMENTO-CA", "Address": null, "City": "WEST SACRAMENTO", "Zipcode": "95691", "Statea": "CA", "FunctDay1": 99.2, "FunctDay3": 99.7, "FunctDay7": 99.8, "FunctDay14": 99.9, "FunctDay30": 99.9, "FunctDay90": 99.9, "PDsNone": 0.625, "PDsSlight": 0.3641, "PDsModerat": 0.0097, "PDsExtensi": 0.0009, "PDsComplet": 0.0001, "PDsExceedS": 0.3749, "PDsExceedM": 0.0108, "PDsExceedE": 0.001, "Latitude_1": 38.58101, "Longitude_": -121.5164, "CountyFips": "06113" }, "geometry": { "type": "Point", "coordinates": [ -121.516399999998612, 38.581010000001697 ] } },
{ "type": "Feature", "properties": { "RailFltyId": "CA000088", "Tract": "06013378000", "Longitude": -122.38609, "Latitude": 37.92024, "stype": null, "lqfsuscat": 0, "lndsuscat": 0, "w_depth": 0.0, "pgv": 20.0, "pga": 0.36, "sa03": 0.72, "sa10": 0.4, "LqfSettlPG": 0.0, "LqfSprPGD": 0.0, "LqfProb": 0.0, "LndPGD": 0.0, "LndProb": 0.0, "SufFltRupt": 0.0, "SurfFltRup": 0.0, "CountyName": "Contra Costa", "RailFlty_1": "CA000088", "TranspFclt": "RDFLT", "eqBldgType": "DFLT", "Tract_1": "06013378000", "Name": "BNSF-RICHMOND-CA", "Address": null, "City": "RICHMOND", "Zipcode": "94801", "Statea": "CA", "FunctDay1": 68.4, "FunctDay3": 81.3, "FunctDay7": 85.8, "FunctDay14": 86.4, "FunctDay30": 87.9, "FunctDay90": 94.3, "PDsNone": 0.0337, "PDsSlight": 0.526, "PDsModerat": 0.269, "PDsExtensi": 0.1283, "PDsComplet": 0.0428, "PDsExceedS": 0.9662, "PDsExceedM": 0.4401, "PDsExceedE": 0.1711, "Latitude_1": 37.92024, "Longitude_": -122.38609, "CountyFips": "06013" }, "geometry": { "type": "Point", "coordinates": [ -122.38609, 37.920240000001286 ] } },
{ "type": "Feature", "properties": { "RailFltyId": "CA000089", "Tract": "06099002002", "Longitude": -120.91469, "Latitude": 37.63673, "stype": null, "lqfsuscat": 0, "lndsuscat": 0, "w_depth": 0.0, "pgv": 4.0, "pga": 0.08, "sa03": 0.24, "sa10": 0.12, "LqfSettlPG": 0.0, "LqfSprPGD": 0.0, "LqfProb": 0.0, "LndPGD": 0.0, "LndProb": 0.0, "SufFltRupt": 0.0, "SurfFltRup": 0.0, "CountyName": "Stanislaus", "RailFlty_1": "CA000089", "TranspFclt": "RDFLT", "eqBldgType": "DFLT", "Tract_1": "06099002002", "Name": "BNSF-MODESTO-CA", "Address": null, "City": "EMPIRE", "Zipcode": "95367", "Statea": "CA", "FunctDay1": 99.2, "FunctDay3": 99.7, "FunctDay7": 99.8, "FunctDay14": 99.9, "FunctDay30": 99.9, "FunctDay90": 99.9, "PDsNone": 0.625, "PDsSlight": 0.3641, "PDsModerat": 0.0097, "PDsExtensi": 0.0009, "PDsComplet": 0.0001, "PDsExceedS": 0.3749, "PDsExceedM": 0.0108, "PDsExceedE": 0.001, "Latitude_1": 37.63673, "Longitude_": -120.91469, "CountyFips": "06099" }, "geometry": { "type": "Point", "coordinates": [ -120.914689999999609, 37.636730000000171 ] } },
{ "type": "Feature", "properties": { "RailFltyId": "CA000090", "Tract": "06077001900", "Longitude": -121.26065, "Latitude": 37.94741, "stype": null, "lqfsuscat": 0, "lndsuscat": 0, "w_depth": 0.0, "pgv": 4.0, "pga": 0.12, "sa03": 0.32, "sa10": 0.12, "LqfSettlPG": 0.0, "LqfSprPGD": 0.0, "LqfProb": 0.0, "LndPGD": 0.0, "LndProb": 0.0, "SufFltRupt": 0.0, "SurfFltRup": 0.0, "CountyName": "San Joaquin", "RailFlty_1": "CA000090", "TranspFclt": "RDFLT", "eqBldgType": "DFLT", "Tract_1": "06077001900", "Name": "BNSF-STOCKTON-CA", "Address": null, "City": "STOCKTON", "Zipcode": "95205", "Statea": "CA", "FunctDay1": 97.1, "FunctDay3": 98.9, "FunctDay7": 99.4, "FunctDay14": 99.5, "FunctDay30": 99.5, "FunctDay90": 99.8, "PDsNone": 0.3972, "PDsSlight": 0.5599, "PDsModerat": 0.0368, "PDsExtensi": 0.0053, "PDsComplet": 0.0006, "PDsExceedS": 0.6027, "PDsExceedM": 0.0428, "PDsExceedE": 0.0059, "Latitude_1": 37.94741, "Longitude_": -121.26065, "CountyFips": "06077" }, "geometry": { "type": "Point", "coordinates": [ -121.26064999999835, 37.947410000000673 ] } },
{ "type": "Feature", "properties": { "RailFltyId": "CA000091", "Tract": "06077005119", "Longitude": -121.27013, "Latitude": 37.85572, "stype": null, "lqfsuscat": 0, "lndsuscat": 0, "w_depth": 0.0, "pgv": 8.0, "pga": 0.12, "sa03": 0.32, "sa10": 0.12, "LqfSettlPG": 0.0, "LqfSprPGD": 0.0, "LqfProb": 0.0, "LndPGD": 0.0, "LndProb": 0.0, "SufFltRupt": 0.0, "SurfFltRup": 0.0, "CountyName": "San Joaquin", "RailFlty_1": "CA000091", "TranspFclt": "RDFLT", "eqBldgType": "DFLT", "Tract_1": "06077005119", "Name": "LATHROP TERMINAL", "Address": null, "City": "FRENCH CAMP", "Zipcode": "95231", "Statea": "CA", "FunctDay1": 97.1, "FunctDay3": 98.9, "FunctDay7": 99.4, "FunctDay14": 99.5, "FunctDay30": 99.5, "FunctDay90": 99.8, "PDsNone": 0.3972, "PDsSlight": 0.5599, "PDsModerat": 0.0368, "PDsExtensi": 0.0053, "PDsComplet": 0.0006, "PDsExceedS": 0.6027, "PDsExceedM": 0.0428, "PDsExceedE": 0.0059, "Latitude_1": 37.85572, "Longitude_": -121.27013, "CountyFips": "06077" }, "geometry": { "type": "Point", "coordinates": [ -121.270129999998971, 37.855720000001384 ] } },
{ "type": "Feature", "properties": { "RailFltyId": "CA000101", "Tract": "06001401900", "Longitude": -122.30743, "Latitude": 37.80818, "stype": null, "lqfsuscat": 5, "lndsuscat": 0, "w_depth": 0.0, "pgv": 24.0, "pga": 0.32, "sa03": 0.64, "sa10": 0.56, "LqfSettlPG": 0.0, "LqfSprPGD": 0.0, "LqfProb": 0.0, "LndPGD": 0.0, "LndProb": 0.0, "SufFltRupt": 0.0, "SurfFltRup": 0.0, "CountyName": "Alameda", "RailFlty_1": "CA000101", "TranspFclt": "RDFLT", "eqBldgType": "DFLT", "Tract_1": "06001401900", "Name": "PACIFIC TRANSLOAD SYSTEM-OAKLAND-CA", "Address": null, "City": "OAKLAND", "Zipcode": "94607", "Statea": "CA", "FunctDay1": 66.2, "FunctDay3": 76.4, "FunctDay7": 80.1, "FunctDay14": 80.7, "FunctDay30": 82.1, "FunctDay90": 88.2, "PDsNone": 0.0427, "PDsSlight": 0.51, "PDsModerat": 0.215, "PDsExtensi": 0.0904, "PDsComplet": 0.1416, "PDsExceedS": 0.9572, "PDsExceedM": 0.4471, "PDsExceedE": 0.232, "Latitude_1": 37.80818, "Longitude_": -122.30743, "CountyFips": "06001" }, "geometry": { "type": "Point", "coordinates": [ -122.307429999998931, 37.80818 ] } },
{ "type": "Feature", "properties": { "RailFltyId": "CA000103", "Tract": "06113011206", "Longitude": -121.75897, "Latitude": 38.69875, "stype": null, "lqfsuscat": 0, "lndsuscat": 0, "w_depth": 0.0, "pgv": 2.0, "pga": 0.08, "sa03": 0.16, "sa10": 0.04, "LqfSettlPG": 0.0, "LqfSprPGD": 0.0, "LqfProb": 0.0, "LndPGD": 0.0, "LndProb": 0.0, "SufFltRupt": 0.0, "SurfFltRup": 0.0, "CountyName": "Yolo", "RailFlty_1": "CA000103", "TranspFclt": "RDFLT", "eqBldgType": "DFLT", "Tract_1": "06113011206", "Name": "DEPENDABLE STORAGE-WOODLAND-CA", "Address": null, "City": "WOODLAND", "Zipcode": "95776", "Statea": "CA", "FunctDay1": 99.2, "FunctDay3": 99.7, "FunctDay7": 99.8, "FunctDay14": 99.9, "FunctDay30": 99.9, "FunctDay90": 99.9, "PDsNone": 0.625, "PDsSlight": 0.3641, "PDsModerat": 0.0097, "PDsExtensi": 0.0009, "PDsComplet": 0.0001, "PDsExceedS": 0.3749, "PDsExceedM": 0.0108, "PDsExceedE": 0.001, "Latitude_1": 38.69875, "Longitude_": -121.75897, "CountyFips": "06113" }, "geometry": { "type": "Point", "coordinates": [ -121.758969999998953, 38.698750000001382 ] } },
{ "type": "Feature", "properties": { "RailFltyId": "CA000106", "Tract": "06001409400", "Longitude": -122.18777, "Latitude": 37.7459, "stype": null, "lqfsuscat": 3, "lndsuscat": 0, "w_depth": 0.0, "pgv": 40.0, "pga": 0.56, "sa03": 1.04, "sa10": 1.12, "LqfSettlPG": 0.0, "LqfSprPGD": 0.0, "LqfProb": 0.0, "LndPGD": 0.0, "LndProb": 0.0, "SufFltRupt": 0.0, "SurfFltRup": 0.0, "CountyName": "Alameda", "RailFlty_1": "CA000106", "TranspFclt": "RDFLT", "eqBldgType": "DFLT", "Tract_1": "06001409400", "Name": "Bay Area Warehouse Company", "Address": null, "City": "Oakland", "Zipcode": "94621", "Statea": "CA", "FunctDay1": 46.3, "FunctDay3": 60.5, "FunctDay7": 65.7, "FunctDay14": 66.9, "FunctDay30": 69.8, "FunctDay90": 82.5, "PDsNone": 0.0066, "PDsSlight": 0.2924, "PDsModerat": 0.2936, "PDsExtensi": 0.2245, "PDsComplet": 0.1827, "PDsExceedS": 0.9933, "PDsExceedM": 0.7008, "PDsExceedE": 0.4072, "Latitude_1": 37.7459, "Longitude_": -122.18777, "CountyFips": "06001" }, "geometry": { "type": "Point", "coordinates": [ -122.187769999998636, 37.745900000001711 ] } },
{ "type": "Feature", "properties": { "RailFltyId": "CA000110", "Tract": "06099002002", "Longitude": -120.91138, "Latitude": 37.63407, "stype": null, "lqfsuscat": 0, "lndsuscat": 0, "w_depth": 0.0, "pgv": 4.0, "pga": 0.08, "sa03": 0.24, "sa10": 0.12, "LqfSettlPG": 0.0, "LqfSprPGD": 0.0, "LqfProb": 0.0, "LndPGD": 0.0, "LndProb": 0.0, "SufFltRupt": 0.0, "SurfFltRup": 0.0, "CountyName": "Stanislaus", "RailFlty_1": "CA000110", "TranspFclt": "RDFLT", "eqBldgType": "DFLT", "Tract_1": "06099002002", "Name": "MODESTO AND EMPIRE TRACTION COMPANY", "Address": null, "City": "MODESTO", "Zipcode": "95357", "Statea": "CA", "FunctDay1": 99.2, "FunctDay3": 99.7, "FunctDay7": 99.8, "FunctDay14": 99.9, "FunctDay30": 99.9, "FunctDay90": 99.9, "PDsNone": 0.625, "PDsSlight": 0.3641, "PDsModerat": 0.0097, "PDsExtensi": 0.0009, "PDsComplet": 0.0001, "PDsExceedS": 0.3749, "PDsExceedM": 0.0108, "PDsExceedE": 0.001, "Latitude_1": 37.63407, "Longitude_": -120.91138, "CountyFips": "06099" }, "geometry": { "type": "Point", "coordinates": [ -120.911379999999554, 37.63407 ] } },
{ "type": "Feature", "properties": { "RailFltyId": "CA000111", "Tract": "06113010901", "Longitude": -121.77762, "Latitude": 38.69195, "stype": null, "lqfsuscat": 0, "lndsuscat": 0, "w_depth": 0.0, "pgv": 2.0, "pga": 0.08, "sa03": 0.16, "sa10": 0.04, "LqfSettlPG": 0.0, "LqfSprPGD": 0.0, "LqfProb": 0.0, "LndPGD": 0.0, "LndProb": 0.0, "SufFltRupt": 0.0, "SurfFltRup": 0.0, "CountyName": "Yolo", "RailFlty_1": "CA000111", "TranspFclt": "RDFLT", "eqBldgType": "DFLT", "Tract_1": "06113010901", "Name": "Pacific International Rice Mill", "Address": null, "City": "Woodland", "Zipcode": "95695", "Statea": "CA", "FunctDay1": 99.2, "FunctDay3": 99.7, "FunctDay7": 99.8, "FunctDay14": 99.9, "FunctDay30": 99.9, "FunctDay90": 99.9, "PDsNone": 0.625, "PDsSlight": 0.3641, "PDsModerat": 0.0097, "PDsExtensi": 0.0009, "PDsComplet": 0.0001, "PDsExceedS": 0.3749, "PDsExceedM": 0.0108, "PDsExceedE": 0.001, "Latitude_1": 38.69195, "Longitude_": -121.77762, "CountyFips": "06113" }, "geometry": { "type": "Point", "coordinates": [ -121.777619999998933, 38.691950000000361 ] } },
{ "type": "Feature", "properties": { "RailFltyId": "CA000112", "Tract": "06077005001", "Longitude": -121.12066, "Latitude": 37.72984, "stype": null, "lqfsuscat": 0, "lndsuscat": 0, "w_depth": 0.0, "pgv": 8.0, "pga": 0.12, "sa03": 0.28, "sa10": 0.08, "LqfSettlPG": 0.0, "LqfSprPGD": 0.0, "LqfProb": 0.0, "LndPGD": 0.0, "LndProb": 0.0, "SufFltRupt": 0.0, "SurfFltRup": 0.0, "CountyName": "San Joaquin", "RailFlty_1": "CA000112", "TranspFclt": "RDFLT", "eqBldgType": "DFLT", "Tract_1": "06077005001", "Name": "Nulaid Foods, Inc.", "Address": null, "City": "Ripon", "Zipcode": "95366", "Statea": "CA", "FunctDay1": 97.1, "FunctDay3": 98.9, "FunctDay7": 99.4, "FunctDay14": 99.5, "FunctDay30": 99.5, "FunctDay90": 99.8, "PDsNone": 0.3972, "PDsSlight": 0.5599, "PDsModerat": 0.0368, "PDsExtensi": 0.0053, "PDsComplet": 0.0006, "PDsExceedS": 0.6027, "PDsExceedM": 0.0428, "PDsExceedE": 0.0059, "Latitude_1": 37.72984, "Longitude_": -121.12066, "CountyFips": "06077" }, "geometry": { "type": "Point", "coordinates": [ -121.120659999998679, 37.72984 ] } },
{ "type": "Feature", "properties": { "RailFltyId": "CA000115", "Tract": "06095250702", "Longitude": -122.24626, "Latitude": 38.08353, "stype": null, "lqfsuscat": 5, "lndsuscat": 0, "w_depth": 0.0, "pgv": 12.0, "pga": 0.24, "sa03": 0.48, "sa10": 0.2, "LqfSettlPG": 0.0, "LqfSprPGD": 0.0, "LqfProb": 0.0, "LndPGD": 0.0, "LndProb": 0.0, "SufFltRupt": 0.0, "SurfFltRup": 0.0, "CountyName": "Solano", "RailFlty_1": "CA000115", "TranspFclt": "RDFLT", "eqBldgType": "DFLT", "Tract_1": "06095250702", "Name": "General Mills, Inc.-Vallejo", "Address": null, "City": "Vallejo", "Zipcode": "94590", "Statea": "CA", "FunctDay1": 80.9, "FunctDay3": 88.6, "FunctDay7": 91.3, "FunctDay14": 91.6, "FunctDay30": 92.3, "FunctDay90": 95.3, "PDsNone": 0.1012, "PDsSlight": 0.6342, "PDsModerat": 0.1626, "PDsExtensi": 0.0501, "PDsComplet": 0.0516, "PDsExceedS": 0.8987, "PDsExceedM": 0.2644, "PDsExceedE": 0.1018, "Latitude_1": 38.08353, "Longitude_": -122.24626, "CountyFips": "06095" }, "geometry": { "type": "Point", "coordinates": [ -122.246259999999893, 38.083530000001701 ] } },
{ "type": "Feature", "properties": { "RailFltyId": "CA000125", "Tract": "06001402000", "Longitude": -122.30456, "Latitude": 37.79528, "stype": null, "lqfsuscat": 5, "lndsuscat": 0, "w_depth": 0.0, "pgv": 20.0, "pga": 0.32, "sa03": 0.68, "sa10": 0.56, "LqfSettlPG": 0.0, "LqfSprPGD": 0.0, "LqfProb": 0.0, "LndPGD": 0.0, "LndProb": 0.0, "SufFltRupt": 0.0, "SurfFltRup": 0.0, "CountyName": "Alameda", "RailFlty_1": "CA000125", "TranspFclt": "RDFLT", "eqBldgType": "DFLT", "Tract_1": "06001402000", "Name": "UP-OAKLAND-CA-1750 FERRO", "Address": null, "City": "OAKLAND", "Zipcode": "94607", "Statea": "CA", "FunctDay1": 66.2, "FunctDay3": 76.4, "FunctDay7": 80.1, "FunctDay14": 80.7, "FunctDay30": 82.1, "FunctDay90": 88.2, "PDsNone": 0.0427, "PDsSlight": 0.51, "PDsModerat": 0.215, "PDsExtensi": 0.0904, "PDsComplet": 0.1416, "PDsExceedS": 0.9572, "PDsExceedM": 0.4471, "PDsExceedE": 0.232, "Latitude_1": 37.79528, "Longitude_": -122.30456, "CountyFips": "06001" }, "geometry": { "type": "Point", "coordinates": [ -122.304559999998673, 37.795280000000275 ] } },
{ "type": "Feature", "properties": { "RailFltyId": "CA000126", "Tract": "06001401900", "Longitude": -122.3075, "Latitude": 37.80135, "stype": null, "lqfsuscat": 5, "lndsuscat": 0, "w_depth": 0.0, "pgv": 24.0, "pga": 0.32, "sa03": 0.64, "sa10": 0.56, "LqfSettlPG": 0.0, "LqfSprPGD": 0.0, "LqfProb": 0.0, "LndPGD": 0.0, "LndProb": 0.0, "SufFltRupt": 0.0, "SurfFltRup": 0.0, "CountyName": "Alameda", "RailFlty_1": "CA000126", "TranspFclt": "RDFLT", "eqBldgType": "DFLT", "Tract_1": "06001401900", "Name": "CSX-OAKLAND-CA-INTERMODAL FACILITY", "Address": null, "City": "OAKLAND", "Zipcode": "94607", "Statea": "CA", "FunctDay1": 66.2, "FunctDay3": 76.4, "FunctDay7": 80.1, "FunctDay14": 80.7, "FunctDay30": 82.1, "FunctDay90": 88.2, "PDsNone": 0.0427, "PDsSlight": 0.51, "PDsModerat": 0.215, "PDsExtensi": 0.0904, "PDsComplet": 0.1416, "PDsExceedS": 0.9572, "PDsExceedM": 0.4471, "PDsExceedE": 0.232, "Latitude_1": 37.80135, "Longitude_": -122.3075, "CountyFips": "06001" }, "geometry": { "type": "Point", "coordinates": [ -122.307499999998981, 37.801350000001548 ] } },
{ "type": "Feature", "properties": { "RailFltyId": "CA000128", "Tract": "06013378000", "Longitude": -122.36675, "Latitude": 37.91135, "stype": null, "lqfsuscat": 1, "lndsuscat": 0, "w_depth": 0.0, "pgv": 20.0, "pga": 0.36, "sa03": 0.8, "sa10": 0.44, "LqfSettlPG": 0.0, "LqfSprPGD": 0.0, "LqfProb": 0.0, "LndPGD": 0.0, "LndProb": 0.0, "SufFltRupt": 0.0, "SurfFltRup": 0.0, "CountyName": "Contra Costa", "RailFlty_1": "CA000128", "TranspFclt": "RDFLT", "eqBldgType": "DFLT", "Tract_1": "06013378000", "Name": "KINDER MORGAN ENERGY PARTNERS, L.P.-RICH", "Address": null, "City": "RICHMOND", "Zipcode": "94804", "Statea": "CA", "FunctDay1": 68.4, "FunctDay3": 81.3, "FunctDay7": 85.8, "FunctDay14": 86.4, "FunctDay30": 87.9, "FunctDay90": 94.3, "PDsNone": 0.0337, "PDsSlight": 0.526, "PDsModerat": 0.269, "PDsExtensi": 0.1283, "PDsComplet": 0.0428, "PDsExceedS": 0.9662, "PDsExceedM": 0.4401, "PDsExceedE": 0.1711, "Latitude_1": 37.91135, "Longitude_": -122.36675, "CountyFips": "06013" }, "geometry": { "type": "Point", "coordinates": [ -122.366749999999229, 37.911350000000311 ] } },
{ "type": "Feature", "properties": { "RailFltyId": "CA000129", "Tract": "06077000800", "Longitude": -121.32204, "Latitude": 37.94536, "stype": null, "lqfsuscat": 0, "lndsuscat": 0, "w_depth": 0.0, "pgv": 4.0, "pga": 0.12, "sa03": 0.32, "sa10": 0.12, "LqfSettlPG": 0.0, "LqfSprPGD": 0.0, "LqfProb": 0.0, "LndPGD": 0.0, "LndProb": 0.0, "SufFltRupt": 0.0, "SurfFltRup": 0.0, "CountyName": "San Joaquin", "RailFlty_1": "CA000129", "TranspFclt": "RDFLT", "eqBldgType": "DFLT", "Tract_1": "06077000800", "Name": "WESTWAY TERMINAL COMPANY, INC.-STOCKTON-", "Address": null, "City": "STOCKTON", "Zipcode": "95203", "Statea": "CA", "FunctDay1": 97.1, "FunctDay3": 98.9, "FunctDay7": 99.4, "FunctDay14": 99.5, "FunctDay30": 99.5, "FunctDay90": 99.8, "PDsNone": 0.3972, "PDsSlight": 0.5599, "PDsModerat": 0.0368, "PDsExtensi": 0.0053, "PDsComplet": 0.0006, "PDsExceedS": 0.6027, "PDsExceedM": 0.0428, "PDsExceedE": 0.0059, "Latitude_1": 37.94536, "Longitude_": -121.32204, "CountyFips": "06077" }, "geometry": { "type": "Point", "coordinates": [ -121.322039999999106, 37.945360000001529 ] } },
{ "type": "Feature", "properties": { "RailFltyId": "CA000130", "Tract": "06077002800", "Longitude": -121.27242, "Latitude": 37.904, "stype": null, "lqfsuscat": 0, "lndsuscat": 0, "w_depth": 0.0, "pgv": 4.0, "pga": 0.12, "sa03": 0.32, "sa10": 0.12, "LqfSettlPG": 0.0, "LqfSprPGD": 0.0, "LqfProb": 0.0, "LndPGD": 0.0, "LndProb": 0.0, "SufFltRupt": 0.0, "SurfFltRup": 0.0, "CountyName": "San Joaquin", "RailFlty_1": "CA000130", "TranspFclt": "RDFLT", "eqBldgType": "DFLT", "Tract_1": "06077002800", "Name": "INTERMODAL INDUSTRIES, INC.-STOCKTON-CA", "Address": null, "City": "STOCKTON", "Zipcode": "95206", "Statea": "CA", "FunctDay1": 97.1, "FunctDay3": 98.9, "FunctDay7": 99.4, "FunctDay14": 99.5, "FunctDay30": 99.5, "FunctDay90": 99.8, "PDsNone": 0.3972, "PDsSlight": 0.5599, "PDsModerat": 0.0368, "PDsExtensi": 0.0053, "PDsComplet": 0.0006, "PDsExceedS": 0.6027, "PDsExceedM": 0.0428, "PDsExceedE": 0.0059, "Latitude_1": 37.904, "Longitude_": -121.27242, "CountyFips": "06077" }, "geometry": { "type": "Point", "coordinates": [ -121.272419999999329, 37.904000000000451 ] } },
{ "type": "Feature", "properties": { "RailFltyId": "CA000135", "Tract": "06001406100", "Longitude": -122.23558, "Latitude": 37.77955, "stype": null, "lqfsuscat": 3, "lndsuscat": 0, "w_depth": 0.0, "pgv": 24.0, "pga": 0.4, "sa03": 0.88, "sa10": 0.6, "LqfSettlPG": 0.0, "LqfSprPGD": 0.0, "LqfProb": 0.0, "LndPGD": 0.0, "LndProb": 0.0, "SufFltRupt": 0.0, "SurfFltRup": 0.0, "CountyName": "Alameda", "RailFlty_1": "CA000135", "TranspFclt": "RDFLT", "eqBldgType": "DFLT", "Tract_1": "06001406100", "Name": "DREISBACH ENTERPRISES-OAKLAND-CA", "Address": null, "City": "OAKLAND", "Zipcode": "94601", "Statea": "CA", "FunctDay1": 62.8, "FunctDay3": 76.4, "FunctDay7": 81.2, "FunctDay14": 81.9, "FunctDay30": 83.8, "FunctDay90": 91.6, "PDsNone": 0.0235, "PDsSlight": 0.4682, "PDsModerat": 0.2831, "PDsExtensi": 0.1511, "PDsComplet": 0.0738, "PDsExceedS": 0.9764, "PDsExceedM": 0.5082, "PDsExceedE": 0.225, "Latitude_1": 37.77955, "Longitude_": -122.23558, "CountyFips": "06001" }, "geometry": { "type": "Point", "coordinates": [ -122.235579999998663, 37.779550000001109 ] } },
{ "type": "Feature", "properties": { "RailFltyId": "CA000150", "Tract": "06013378000", "Longitude": -122.41675, "Latitude": 37.95074, "stype": null, "lqfsuscat": 1, "lndsuscat": 0, "w_depth": 0.0, "pgv": 12.0, "pga": 0.32, "sa03": 0.6, "sa10": 0.2, "LqfSettlPG": 0.0, "LqfSprPGD": 0.0, "LqfProb": 0.0, "LndPGD": 0.0, "LndProb": 0.0, "SufFltRupt": 0.0, "SurfFltRup": 0.0, "CountyName": "Contra Costa", "RailFlty_1": "CA000150", "TranspFclt": "RDFLT", "eqBldgType": "DFLT", "Tract_1": "06013378000", "Name": "PAKTANK - RICHMOND TERMINAL-RICHMOND-CA", "Address": null, "City": "RICHMOND", "Zipcode": "94801", "Statea": "CA", "FunctDay1": 73.4, "FunctDay3": 85.0, "FunctDay7": 89.1, "FunctDay14": 89.5, "FunctDay30": 90.7, "FunctDay90": 95.7, "PDsNone": 0.0483, "PDsSlight": 0.5766, "PDsModerat": 0.2431, "PDsExtensi": 0.1022, "PDsComplet": 0.0295, "PDsExceedS": 0.9516, "PDsExceedM": 0.3749, "PDsExceedE": 0.1318, "Latitude_1": 37.95074, "Longitude_": -122.41675, "CountyFips": "06013" }, "geometry": { "type": "Point", "coordinates": [ -122.416749999998501, 37.950740000000224 ] } },
{ "type": "Feature", "properties": { "RailFltyId": "CA000151", "Tract": "06013378000", "Longitude": -122.36599, "Latitude": 37.92124, "stype": null, "lqfsuscat": 0, "lndsuscat": 0, "w_depth": 0.0, "pgv": 24.0, "pga": 0.4, "sa03": 0.76, "sa10": 0.52, "LqfSettlPG": 0.0, "LqfSprPGD": 0.0, "LqfProb": 0.0, "LndPGD": 0.0, "LndProb": 0.0, "SufFltRupt": 0.0, "SurfFltRup": 0.0, "CountyName": "Contra Costa", "RailFlty_1": "CA000151", "TranspFclt": "RDFLT", "eqBldgType": "DFLT", "Tract_1": "06013378000", "Name": "LEVIN RICHMOND TERMINAL CORPORATION-RICH", "Address": null, "City": "RICHMOND", "Zipcode": "94804", "Statea": "CA", "FunctDay1": 63.7, "FunctDay3": 77.5, "FunctDay7": 82.4, "FunctDay14": 83.1, "FunctDay30": 85.0, "FunctDay90": 92.6, "PDsNone": 0.0239, "PDsSlight": 0.476, "PDsModerat": 0.2879, "PDsExtensi": 0.1537, "PDsComplet": 0.0583, "PDsExceedS": 0.976, "PDsExceedM": 0.5, "PDsExceedE": 0.212, "Latitude_1": 37.92124, "Longitude_": -122.36599, "CountyFips": "06013" }, "geometry": { "type": "Point", "coordinates": [ -122.365989999998419, 37.92124000000149 ] } },
{ "type": "Feature", "properties": { "RailFltyId": "CA000152", "Tract": "06013305000", "Longitude": -121.81385, "Latitude": 38.01689, "stype": null, "lqfsuscat": 2, "lndsuscat": 0, "w_depth": 0.0, "pgv": 8.0, "pga": 0.2, "sa03": 0.44, "sa10": 0.2, "LqfSettlPG": 0.0, "LqfSprPGD": 0.0, "LqfProb": 0.0, "LndPGD": 0.0, "LndProb": 0.0, "SufFltRupt": 0.0, "SurfFltRup": 0.0, "CountyName": "Contra Costa", "RailFlty_1": "CA000152", "TranspFclt": "RDFLT", "eqBldgType": "DFLT", "Tract_1": "06013305000", "Name": "ANTIOCH RAIL AND TRANSLOADING-ANTIOCH-CA", "Address": null, "City": "ANTIOCH", "Zipcode": "94509", "Statea": "CA", "FunctDay1": 89.0, "FunctDay3": 94.9, "FunctDay7": 96.9, "FunctDay14": 97.1, "FunctDay30": 97.4, "FunctDay90": 98.9, "PDsNone": 0.1611, "PDsSlight": 0.6777, "PDsModerat": 0.1242, "PDsExtensi": 0.0315, "PDsComplet": 0.0053, "PDsExceedS": 0.8388, "PDsExceedM": 0.1611, "PDsExceedE": 0.0368, "Latitude_1": 38.01689, "Longitude_": -121.81385, "CountyFips": "06013" }, "geometry": { "type": "Point", "coordinates": [ -121.813849999998638, 38.016890000000785 ] } },
{ "type": "Feature", "properties": { "RailFltyId": "CA000153", "Tract": "06099002002", "Longitude": -120.92027, "Latitude": 37.62773, "stype": null, "lqfsuscat": 0, "lndsuscat": 0, "w_depth": 0.0, "pgv": 8.0, "pga": 0.08, "sa03": 0.24, "sa10": 0.12, "LqfSettlPG": 0.0, "LqfSprPGD": 0.0, "LqfProb": 0.0, "LndPGD": 0.0, "LndProb": 0.0, "SufFltRupt": 0.0, "SurfFltRup": 0.0, "CountyName": "Stanislaus", "RailFlty_1": "CA000153", "TranspFclt": "RDFLT", "eqBldgType": "DFLT", "Tract_1": "06099002002", "Name": "SIERRA PACIFIC-MODESTO-CA", "Address": null, "City": "MODESTO", "Zipcode": "95357", "Statea": "CA", "FunctDay1": 99.2, "FunctDay3": 99.7, "FunctDay7": 99.8, "FunctDay14": 99.9, "FunctDay30": 99.9, "FunctDay90": 99.9, "PDsNone": 0.625, "PDsSlight": 0.3641, "PDsModerat": 0.0097, "PDsExtensi": 0.0009, "PDsComplet": 0.0001, "PDsExceedS": 0.3749, "PDsExceedM": 0.0108, "PDsExceedE": 0.001, "Latitude_1": 37.62773, "Longitude_": -120.92027, "CountyFips": "06099" }, "geometry": { "type": "Point", "coordinates": [ -120.920269999998709, 37.627730000000156 ] } },
{ "type": "Feature", "properties": { "RailFltyId": "CA000154", "Tract": "06099002002", "Longitude": -120.93765, "Latitude": 37.63129, "stype": null, "lqfsuscat": 0, "lndsuscat": 0, "w_depth": 0.0, "pgv": 8.0, "pga": 0.08, "sa03": 0.24, "sa10": 0.08, "LqfSettlPG": 0.0, "LqfSprPGD": 0.0, "LqfProb": 0.0, "LndPGD": 0.0, "LndProb": 0.0, "SufFltRupt": 0.0, "SurfFltRup": 0.0, "CountyName": "Stanislaus", "RailFlty_1": "CA000154", "TranspFclt": "RDFLT", "eqBldgType": "DFLT", "Tract_1": "06099002002", "Name": "RAIL DELIVERY SERVICES-MODESTO-CA", "Address": null, "City": "MODESTO", "Zipcode": "95354", "Statea": "CA", "FunctDay1": 99.2, "FunctDay3": 99.7, "FunctDay7": 99.8, "FunctDay14": 99.9, "FunctDay30": 99.9, "FunctDay90": 99.9, "PDsNone": 0.625, "PDsSlight": 0.3641, "PDsModerat": 0.0097, "PDsExtensi": 0.0009, "PDsComplet": 0.0001, "PDsExceedS": 0.3749, "PDsExceedM": 0.0108, "PDsExceedE": 0.001, "Latitude_1": 37.63129, "Longitude_": -120.93765, "CountyFips": "06099" }, "geometry": { "type": "Point", "coordinates": [ -120.937649999999849, 37.631290000001172 ] } },
{ "type": "Feature", "properties": { "RailFltyId": "CA000155", "Tract": "06113010203", "Longitude": -121.57764, "Latitude": 38.57378, "stype": null, "lqfsuscat": 0, "lndsuscat": 0, "w_depth": 0.0, "pgv": 2.0, "pga": 0.08, "sa03": 0.16, "sa10": 0.04, "LqfSettlPG": 0.0, "LqfSprPGD": 0.0, "LqfProb": 0.0, "LndPGD": 0.0, "LndProb": 0.0, "SufFltRupt": 0.0, "SurfFltRup": 0.0, "CountyName": "Yolo", "RailFlty_1": "CA000155", "TranspFclt": "RDFLT", "eqBldgType": "DFLT", "Tract_1": "06113010203", "Name": "CALIFORNIA DISTRIBUTION CENTERS\/MCLAUGHL", "Address": null, "City": "WEST SACRAMENTO", "Zipcode": "95691", "Statea": "CA", "FunctDay1": 99.2, "FunctDay3": 99.7, "FunctDay7": 99.8, "FunctDay14": 99.9, "FunctDay30": 99.9, "FunctDay90": 99.9, "PDsNone": 0.625, "PDsSlight": 0.3641, "PDsModerat": 0.0097, "PDsExtensi": 0.0009, "PDsComplet": 0.0001, "PDsExceedS": 0.3749, "PDsExceedM": 0.0108, "PDsExceedE": 0.001, "Latitude_1": 38.57378, "Longitude_": -121.57764, "CountyFips": "06113" }, "geometry": { "type": "Point", "coordinates": [ -121.577639999999519, 38.573780000000625 ] } },
{ "type": "Feature", "properties": { "RailFltyId": "CA000156", "Tract": "06077000800", "Longitude": -121.32338, "Latitude": 37.94527, "stype": null, "lqfsuscat": 0, "lndsuscat": 0, "w_depth": 0.0, "pgv": 4.0, "pga": 0.12, "sa03": 0.32, "sa10": 0.12, "LqfSettlPG": 0.0, "LqfSprPGD": 0.0, "LqfProb": 0.0, "LndPGD": 0.0, "LndProb": 0.0, "SufFltRupt": 0.0, "SurfFltRup": 0.0, "CountyName": "San Joaquin", "RailFlty_1": "CA000156", "TranspFclt": "RDFLT", "eqBldgType": "DFLT", "Tract_1": "06077000800", "Name": "WEST COAST WAREHOUSING-STOCKTON-CA", "Address": null, "City": "STOCKTON", "Zipcode": "95203", "Statea": "CA", "FunctDay1": 97.1, "FunctDay3": 98.9, "FunctDay7": 99.4, "FunctDay14": 99.5, "FunctDay30": 99.5, "FunctDay90": 99.8, "PDsNone": 0.3972, "PDsSlight": 0.5599, "PDsModerat": 0.0368, "PDsExtensi": 0.0053, "PDsComplet": 0.0006, "PDsExceedS": 0.6027, "PDsExceedM": 0.0428, "PDsExceedE": 0.0059, "Latitude_1": 37.94527, "Longitude_": -121.32338, "CountyFips": "06077" }, "geometry": { "type": "Point", "coordinates": [ -121.323379999999815, 37.945270000000164 ] } },
{ "type": "Feature", "properties": { "RailFltyId": "CA000157", "Tract": "06077000800", "Longitude": -121.3257, "Latitude": 37.94513, "stype": null, "lqfsuscat": 0, "lndsuscat": 0, "w_depth": 0.0, "pgv": 4.0, "pga": 0.12, "sa03": 0.32, "sa10": 0.12, "LqfSettlPG": 0.0, "LqfSprPGD": 0.0, "LqfProb": 0.0, "LndPGD": 0.0, "LndProb": 0.0, "SufFltRupt": 0.0, "SurfFltRup": 0.0, "CountyName": "San Joaquin", "RailFlty_1": "CA000157", "TranspFclt": "RDFLT", "eqBldgType": "DFLT", "Tract_1": "06077000800", "Name": "STOCKTON TRANSMODAL, INC.-STOCKTON-CA", "Address": null, "City": "STOCKTON", "Zipcode": "95203", "Statea": "CA", "FunctDay1": 97.1, "FunctDay3": 98.9, "FunctDay7": 99.4, "FunctDay14": 99.5, "FunctDay30": 99.5, "FunctDay90": 99.8, "PDsNone": 0.3972, "PDsSlight": 0.5599, "PDsModerat": 0.0368, "PDsExtensi": 0.0053, "PDsComplet": 0.0006, "PDsExceedS": 0.6027, "PDsExceedM": 0.0428, "PDsExceedE": 0.0059, "Latitude_1": 37.94513, "Longitude_": -121.3257, "CountyFips": "06077" }, "geometry": { "type": "Point", "coordinates": [ -121.325699999999415, 37.94513 ] } },
{ "type": "Feature", "properties": { "RailFltyId": "CA000158", "Tract": "06077000800", "Longitude": -121.32338, "Latitude": 37.94527, "stype": null, "lqfsuscat": 0, "lndsuscat": 0, "w_depth": 0.0, "pgv": 4.0, "pga": 0.12, "sa03": 0.32, "sa10": 0.12, "LqfSettlPG": 0.0, "LqfSprPGD": 0.0, "LqfProb": 0.0, "LndPGD": 0.0, "LndProb": 0.0, "SufFltRupt": 0.0, "SurfFltRup": 0.0, "CountyName": "San Joaquin", "RailFlty_1": "CA000158", "TranspFclt": "RDFLT", "eqBldgType": "DFLT", "Tract_1": "06077000800", "Name": "GKA ENTERPRISES-STOCKTON-CA", "Address": null, "City": "STOCKTON", "Zipcode": "95203", "Statea": "CA", "FunctDay1": 97.1, "FunctDay3": 98.9, "FunctDay7": 99.4, "FunctDay14": 99.5, "FunctDay30": 99.5, "FunctDay90": 99.8, "PDsNone": 0.3972, "PDsSlight": 0.5599, "PDsModerat": 0.0368, "PDsExtensi": 0.0053, "PDsComplet": 0.0006, "PDsExceedS": 0.6027, "PDsExceedM": 0.0428, "PDsExceedE": 0.0059, "Latitude_1": 37.94527, "Longitude_": -121.32338, "CountyFips": "06077" }, "geometry": { "type": "Point", "coordinates": [ -121.323379999999815, 37.945270000000164 ] } },
{ "type": "Feature", "properties": { "RailFltyId": "CA000159", "Tract": "06077001600", "Longitude": -121.26393, "Latitude": 37.96045, "stype": null, "lqfsuscat": 0, "lndsuscat": 0, "w_depth": 0.0, "pgv": 4.0, "pga": 0.12, "sa03": 0.32, "sa10": 0.12, "LqfSettlPG": 0.0, "LqfSprPGD": 0.0, "LqfProb": 0.0, "LndPGD": 0.0, "LndProb": 0.0, "SufFltRupt": 0.0, "SurfFltRup": 0.0, "CountyName": "San Joaquin", "RailFlty_1": "CA000159", "TranspFclt": "RDFLT", "eqBldgType": "DFLT", "Tract_1": "06077001600", "Name": "ROMAR METALS, INC.-STOCKTON-CA", "Address": null, "City": "STOCKTON", "Zipcode": "95205", "Statea": "CA", "FunctDay1": 97.1, "FunctDay3": 98.9, "FunctDay7": 99.4, "FunctDay14": 99.5, "FunctDay30": 99.5, "FunctDay90": 99.8, "PDsNone": 0.3972, "PDsSlight": 0.5599, "PDsModerat": 0.0368, "PDsExtensi": 0.0053, "PDsComplet": 0.0006, "PDsExceedS": 0.6027, "PDsExceedM": 0.0428, "PDsExceedE": 0.0059, "Latitude_1": 37.96045, "Longitude_": -121.26393, "CountyFips": "06077" }, "geometry": { "type": "Point", "coordinates": [ -121.263929999999164, 37.960450000000492 ] } },
{ "type": "Feature", "properties": { "RailFltyId": "CA000160", "Tract": "06077001700", "Longitude": -121.26728, "Latitude": 37.97396, "stype": null, "lqfsuscat": 0, "lndsuscat": 0, "w_depth": 0.0, "pgv": 4.0, "pga": 0.12, "sa03": 0.28, "sa10": 0.12, "LqfSettlPG": 0.0, "LqfSprPGD": 0.0, "LqfProb": 0.0, "LndPGD": 0.0, "LndProb": 0.0, "SufFltRupt": 0.0, "SurfFltRup": 0.0, "CountyName": "San Joaquin", "RailFlty_1": "CA000160", "TranspFclt": "RDFLT", "eqBldgType": "DFLT", "Tract_1": "06077001700", "Name": "KEEP ON TRUCKING COMPANY, INC.-STOCKTON-", "Address": null, "City": "STOCKTON", "Zipcode": "95205", "Statea": "CA", "FunctDay1": 97.1, "FunctDay3": 98.9, "FunctDay7": 99.4, "FunctDay14": 99.5, "FunctDay30": 99.5, "FunctDay90": 99.8, "PDsNone": 0.3972, "PDsSlight": 0.5599, "PDsModerat": 0.0368, "PDsExtensi": 0.0053, "PDsComplet": 0.0006, "PDsExceedS": 0.6027, "PDsExceedM": 0.0428, "PDsExceedE": 0.0059, "Latitude_1": 37.97396, "Longitude_": -121.26728, "CountyFips": "06077" }, "geometry": { "type": "Point", "coordinates": [ -121.26728, 37.973960000001171 ] } },
{ "type": "Feature", "properties": { "RailFltyId": "CA000161", "Tract": "06077002701", "Longitude": -121.237, "Latitude": 37.97067, "stype": null, "lqfsuscat": 0, "lndsuscat": 0, "w_depth": 0.0, "pgv": 4.0, "pga": 0.12, "sa03": 0.28, "sa10": 0.12, "LqfSettlPG": 0.0, "LqfSprPGD": 0.0, "LqfProb": 0.0, "LndPGD": 0.0, "LndProb": 0.0, "SufFltRupt": 0.0, "SurfFltRup": 0.0, "CountyName": "San Joaquin", "RailFlty_1": "CA000161", "TranspFclt": "RDFLT", "eqBldgType": "DFLT", "Tract_1": "06077002701", "Name": "CHEMICAL TRANSFER COMPANY, INC.-STOCKTON", "Address": null, "City": "STOCKTON", "Zipcode": "95215", "Statea": "CA", "FunctDay1": 97.1, "FunctDay3": 98.9, "FunctDay7": 99.4, "FunctDay14": 99.5, "FunctDay30": 99.5, "FunctDay90": 99.8, "PDsNone": 0.3972, "PDsSlight": 0.5599, "PDsModerat": 0.0368, "PDsExtensi": 0.0053, "PDsComplet": 0.0006, "PDsExceedS": 0.6027, "PDsExceedM": 0.0428, "PDsExceedE": 0.0059, "Latitude_1": 37.97067, "Longitude_": -121.237, "CountyFips": "06077" }, "geometry": { "type": "Point", "coordinates": [ -121.236999999999171, 37.970670000000609 ] } },
{ "type": "Feature", "properties": { "RailFltyId": "CA000162", "Tract": "06077002701", "Longitude": -121.23948, "Latitude": 37.97217, "stype": null, "lqfsuscat": 0, "lndsuscat": 0, "w_depth": 0.0, "pgv": 4.0, "pga": 0.12, "sa03": 0.28, "sa10": 0.12, "LqfSettlPG": 0.0, "LqfSprPGD": 0.0, "LqfProb": 0.0, "LndPGD": 0.0, "LndProb": 0.0, "SufFltRupt": 0.0, "SurfFltRup": 0.0, "CountyName": "San Joaquin", "RailFlty_1": "CA000162", "TranspFclt": "RDFLT", "eqBldgType": "DFLT", "Tract_1": "06077002701", "Name": "BEST LOGISTICS, INC.-STOCKTON-CA", "Address": null, "City": "STOCKTON", "Zipcode": "95215", "Statea": "CA", "FunctDay1": 97.1, "FunctDay3": 98.9, "FunctDay7": 99.4, "FunctDay14": 99.5, "FunctDay30": 99.5, "FunctDay90": 99.8, "PDsNone": 0.3972, "PDsSlight": 0.5599, "PDsModerat": 0.0368, "PDsExtensi": 0.0053, "PDsComplet": 0.0006, "PDsExceedS": 0.6027, "PDsExceedM": 0.0428, "PDsExceedE": 0.0059, "Latitude_1": 37.97217, "Longitude_": -121.23948, "CountyFips": "06077" }, "geometry": { "type": "Point", "coordinates": [ -121.239479999998366, 37.972170000000915 ] } },
{ "type": "Feature", "properties": { "RailFltyId": "CA000163", "Tract": "06077003700", "Longitude": -121.231, "Latitude": 37.93971, "stype": null, "lqfsuscat": 0, "lndsuscat": 0, "w_depth": 0.0, "pgv": 4.0, "pga": 0.12, "sa03": 0.28, "sa10": 0.12, "LqfSettlPG": 0.0, "LqfSprPGD": 0.0, "LqfProb": 0.0, "LndPGD": 0.0, "LndProb": 0.0, "SufFltRupt": 0.0, "SurfFltRup": 0.0, "CountyName": "San Joaquin", "RailFlty_1": "CA000163", "TranspFclt": "RDFLT", "eqBldgType": "DFLT", "Tract_1": "06077003700", "Name": "FAIRVIEW DISTRIBUTION CENTERS, INC.-STOC", "Address": null, "City": "STOCKTON", "Zipcode": "95215", "Statea": "CA", "FunctDay1": 97.1, "FunctDay3": 98.9, "FunctDay7": 99.4, "FunctDay14": 99.5, "FunctDay30": 99.5, "FunctDay90": 99.8, "PDsNone": 0.3972, "PDsSlight": 0.5599, "PDsModerat": 0.0368, "PDsExtensi": 0.0053, "PDsComplet": 0.0006, "PDsExceedS": 0.6027, "PDsExceedM": 0.0428, "PDsExceedE": 0.0059, "Latitude_1": 37.93971, "Longitude_": -121.231, "CountyFips": "06077" }, "geometry": { "type": "Point", "coordinates": [ -121.230999999999767, 37.939710000000559 ] } },
{ "type": "Feature", "properties": { "RailFltyId": "CA000187", "Tract": "06047001901", "Longitude": -120.37901, "Latitude": 37.29383, "stype": null, "lqfsuscat": 0, "lndsuscat": 0, "w_depth": 0.0, "pgv": 4.0, "pga": 0.04, "sa03": 0.12, "sa10": 0.08, "LqfSettlPG": 0.0, "LqfSprPGD": 0.0, "LqfProb": 0.0, "LndPGD": 0.0, "LndProb": 0.0, "SufFltRupt": 0.0, "SurfFltRup": 0.0, "CountyName": "Merced", "RailFlty_1": "CA000187", "TranspFclt": "RDFLT", "eqBldgType": "DFLT", "Tract_1": "06047001901", "Name": "WALLACE TRANSPORT\/ CASCADE DRAYAGE AND W", "Address": null, "City": "MERCED", "Zipcode": "95340", "Statea": "CA", "FunctDay1": 99.9, "FunctDay3": 99.9, "FunctDay7": 99.9, "FunctDay14": 99.9, "FunctDay30": 99.9, "FunctDay90": 99.9, "PDsNone": 0.9046, "PDsSlight": 0.0947, "PDsModerat": 0.0006, "PDsExtensi": 0.0, "PDsComplet": 0.0, "PDsExceedS": 0.0953, "PDsExceedM": 0.0006, "PDsExceedE": 0.0, "Latitude_1": 37.29383, "Longitude_": -120.37901, "CountyFips": "06047" }, "geometry": { "type": "Point", "coordinates": [ -120.379009999998743, 37.293830000000526 ] } },
{ "type": "Feature", "properties": { "RailFltyId": "CA000194", "Tract": "06085500300", "Longitude": -121.90577, "Latitude": 37.33687, "stype": null, "lqfsuscat": 3, "lndsuscat": 0, "w_depth": 0.0, "pgv": 20.0, "pga": 0.28, "sa03": 0.6, "sa10": 0.36, "LqfSettlPG": 0.0, "LqfSprPGD": 0.0, "LqfProb": 0.0, "LndPGD": 0.0, "LndProb": 0.0, "SufFltRupt": 0.0, "SurfFltRup": 0.0, "CountyName": "Santa Clara", "RailFlty_1": "CA000194", "TranspFclt": "RDFLT", "eqBldgType": "DFLT", "Tract_1": "06085500300", "Name": "SAN JOSE DISTRIBUTION SERVICES-SAN JOSE-", "Address": null, "City": "SAN JOSE", "Zipcode": "95110", "Statea": "CA", "FunctDay1": 78.4, "FunctDay3": 88.3, "FunctDay7": 91.8, "FunctDay14": 92.2, "FunctDay30": 93.0, "FunctDay90": 96.8, "PDsNone": 0.0704, "PDsSlight": 0.6217, "PDsModerat": 0.2091, "PDsExtensi": 0.0761, "PDsComplet": 0.0224, "PDsExceedS": 0.9295, "PDsExceedM": 0.3077, "PDsExceedE": 0.0986, "Latitude_1": 37.33687, "Longitude_": -121.90577, "CountyFips": "06085" }, "geometry": { "type": "Point", "coordinates": [ -121.905769999999393, 37.336870000000999 ] } },
{ "type": "Feature", "properties": { "RailFltyId": "CA000196", "Tract": "06001401900", "Longitude": -122.30743, "Latitude": 37.80818, "stype": null, "lqfsuscat": 5, "lndsuscat": 0, "w_depth": 0.0, "pgv": 24.0, "pga": 0.32, "sa03": 0.64, "sa10": 0.56, "LqfSettlPG": 0.0, "LqfSprPGD": 0.0, "LqfProb": 0.0, "LndPGD": 0.0, "LndProb": 0.0, "SufFltRupt": 0.0, "SurfFltRup": 0.0, "CountyName": "Alameda", "RailFlty_1": "CA000196", "TranspFclt": "RDFLT", "eqBldgType": "DFLT", "Tract_1": "06001401900", "Name": "PACIFIC COAST CONTAINER CO.-OAKLAND-CA", "Address": null, "City": "OAKLAND", "Zipcode": "94607", "Statea": "CA", "FunctDay1": 66.2, "FunctDay3": 76.4, "FunctDay7": 80.1, "FunctDay14": 80.7, "FunctDay30": 82.1, "FunctDay90": 88.2, "PDsNone": 0.0427, "PDsSlight": 0.51, "PDsModerat": 0.215, "PDsExtensi": 0.0904, "PDsComplet": 0.1416, "PDsExceedS": 0.9572, "PDsExceedM": 0.4471, "PDsExceedE": 0.232, "Latitude_1": 37.80818, "Longitude_": -122.30743, "CountyFips": "06001" }, "geometry": { "type": "Point", "coordinates": [ -122.307429999998931, 37.80818 ] } },
{ "type": "Feature", "properties": { "RailFltyId": "CA000198", "Tract": "06013365002", "Longitude": -122.35952, "Latitude": 37.95477, "stype": null, "lqfsuscat": 3, "lndsuscat": 0, "w_depth": 0.0, "pgv": 36.0, "pga": 0.56, "sa03": 1.04, "sa10": 0.68, "LqfSettlPG": 0.0, "LqfSprPGD": 0.0, "LqfProb": 0.0, "LndPGD": 0.0, "LndProb": 0.0, "SufFltRupt": 0.0, "SurfFltRup": 0.0, "CountyName": "Contra Costa", "RailFlty_1": "CA000198", "TranspFclt": "RDFLT", "eqBldgType": "DFLT", "Tract_1": "06013365002", "Name": "BUDWAY ENTERPRISES, INC.-RICHMOND-CA", "Address": null, "City": "RICHMOND", "Zipcode": "94801", "Statea": "CA", "FunctDay1": 46.3, "FunctDay3": 60.5, "FunctDay7": 65.7, "FunctDay14": 66.9, "FunctDay30": 69.8, "FunctDay90": 82.5, "PDsNone": 0.0066, "PDsSlight": 0.2924, "PDsModerat": 0.2936, "PDsExtensi": 0.2245, "PDsComplet": 0.1827, "PDsExceedS": 0.9933, "PDsExceedM": 0.7008, "PDsExceedE": 0.4072, "Latitude_1": 37.95477, "Longitude_": -122.35952, "CountyFips": "06013" }, "geometry": { "type": "Point", "coordinates": [ -122.35952, 37.954770000000281 ] } },
{ "type": "Feature", "properties": { "RailFltyId": "CA000019", "Tract": "06001441700", "Longitude": -122.006378, "Latitude": 37.558197, "stype": null, "lqfsuscat": 3, "lndsuscat": 0, "w_depth": 0.0, "pgv": 28.0, "pga": 0.52, "sa03": 1.04, "sa10": 0.64, "LqfSettlPG": 0.0, "LqfSprPGD": 0.0, "LqfProb": 0.0, "LndPGD": 0.0, "LndProb": 0.0, "SufFltRupt": 0.0, "SurfFltRup": 0.0, "CountyName": "Alameda", "RailFlty_1": "CA000019", "TranspFclt": "RDFLT", "eqBldgType": "DFLT", "Tract_1": "06001441700", "Name": "Fremont (Trains, Capitol Buses), Califor", "Address": "37260 Fremont Blvd.", "City": "Fremont", "Zipcode": "94536", "Statea": "CA", "FunctDay1": 49.9, "FunctDay3": 64.2, "FunctDay7": 69.4, "FunctDay14": 70.5, "FunctDay30": 73.2, "FunctDay90": 84.8, "PDsNone": 0.0089, "PDsSlight": 0.3297, "PDsModerat": 0.2971, "PDsExtensi": 0.2099, "PDsComplet": 0.1542, "PDsExceedS": 0.991, "PDsExceedM": 0.6613, "PDsExceedE": 0.3641, "Latitude_1": 37.558197, "Longitude_": -122.006378, "CountyFips": "06001" }, "geometry": { "type": "Point", "coordinates": [ -122.006379999998899, 37.558200000001307 ] } },
{ "type": "Feature", "properties": { "RailFltyId": "CA000027", "Tract": "06085505007", "Longitude": -121.946411, "Latitude": 37.37851, "stype": null, "lqfsuscat": 3, "lndsuscat": 0, "w_depth": 0.0, "pgv": 16.0, "pga": 0.32, "sa03": 0.72, "sa10": 0.28, "LqfSettlPG": 0.0, "LqfSprPGD": 0.0, "LqfProb": 0.0, "LndPGD": 0.0, "LndProb": 0.0, "SufFltRupt": 0.0, "SurfFltRup": 0.0, "CountyName": "Santa Clara", "RailFlty_1": "CA000027", "TranspFclt": "RDFLT", "eqBldgType": "DFLT", "Tract_1": "06085505007", "Name": "Santa Clara (Great America), California", "Address": "5099 Stars & Stripes Dr.", "City": "Santa Clara", "Zipcode": "95054", "Statea": "CA", "FunctDay1": 72.9, "FunctDay3": 84.4, "FunctDay7": 88.5, "FunctDay14": 88.9, "FunctDay30": 90.1, "FunctDay90": 95.2, "PDsNone": 0.0479, "PDsSlight": 0.572, "PDsModerat": 0.2412, "PDsExtensi": 0.1013, "PDsComplet": 0.0373, "PDsExceedS": 0.952, "PDsExceedM": 0.3799, "PDsExceedE": 0.1387, "Latitude_1": 37.37851, "Longitude_": -121.946411, "CountyFips": "06085" }, "geometry": { "type": "Point", "coordinates": [ -121.94640999999865, 37.37851000000046 ] } },
{ "type": "Feature", "properties": { "RailFltyId": "CA000068", "Tract": "06053001800", "Longitude": -121.656189, "Latitude": 36.679363, "stype": null, "lqfsuscat": 0, "lndsuscat": 0, "w_depth": 0.0, "pgv": 8.0, "pga": 0.08, "sa03": 0.2, "sa10": 0.12, "LqfSettlPG": 0.0, "LqfSprPGD": 0.0, "LqfProb": 0.0, "LndPGD": 0.0, "LndProb": 0.0, "SufFltRupt": 0.0, "SurfFltRup": 0.0, "CountyName": "Monterey", "RailFlty_1": "CA000068", "TranspFclt": "RDFLT", "eqBldgType": "DFLT", "Tract_1": "06053001800", "Name": "Salinas, California", "Address": "30 Railroad Avenue", "City": "Salinas", "Zipcode": "93901-1432", "Statea": "CA", "FunctDay1": 99.2, "FunctDay3": 99.7, "FunctDay7": 99.8, "FunctDay14": 99.9, "FunctDay30": 99.9, "FunctDay90": 99.9, "PDsNone": 0.625, "PDsSlight": 0.3641, "PDsModerat": 0.0097, "PDsExtensi": 0.0009, "PDsComplet": 0.0001, "PDsExceedS": 0.3749, "PDsExceedM": 0.0108, "PDsExceedE": 0.001, "Latitude_1": 36.679363, "Longitude_": -121.656189, "CountyFips": "06053" }, "geometry": { "type": "Point", "coordinates": [ -121.656189999999697, 36.67936 ] } },
{ "type": "Feature", "properties": { "RailFltyId": "CA000069", "Tract": "06013376000", "Longitude": -122.35305, "Latitude": 37.936085, "stype": null, "lqfsuscat": 3, "lndsuscat": 0, "w_depth": 0.0, "pgv": 32.0, "pga": 0.48, "sa03": 0.84, "sa10": 0.68, "LqfSettlPG": 0.0, "LqfSprPGD": 0.0, "LqfProb": 0.0, "LndPGD": 0.0, "LndProb": 0.0, "SufFltRupt": 0.0, "SurfFltRup": 0.0, "CountyName": "Contra Costa", "RailFlty_1": "CA000069", "TranspFclt": "RDFLT", "eqBldgType": "DFLT", "Tract_1": "06013376000", "Name": "Richmond, California", "Address": "1700 Nevin Avenue", "City": "Richmond", "Zipcode": "94802", "Statea": "CA", "FunctDay1": 53.9, "FunctDay3": 68.2, "FunctDay7": 73.4, "FunctDay14": 74.3, "FunctDay30": 76.8, "FunctDay90": 87.2, "PDsNone": 0.0122, "PDsSlight": 0.3723, "PDsModerat": 0.2979, "PDsExtensi": 0.1932, "PDsComplet": 0.1242, "PDsExceedS": 0.9877, "PDsExceedM": 0.6154, "PDsExceedE": 0.3175, "Latitude_1": 37.936085, "Longitude_": -122.35305, "CountyFips": "06013" }, "geometry": { "type": "Point", "coordinates": [ -122.353049999999712, 37.936080000001311 ] } },
{ "type": "Feature", "properties": { "RailFltyId": "CA000102", "Tract": "06085503103", "Longitude": -121.86129, "Latitude": 37.31019, "stype": null, "lqfsuscat": 4, "lndsuscat": 0, "w_depth": 0.0, "pgv": 16.0, "pga": 0.28, "sa03": 0.56, "sa10": 0.32, "LqfSettlPG": 0.0, "LqfSprPGD": 0.0, "LqfProb": 0.0, "LndPGD": 0.0, "LndProb": 0.0, "SufFltRupt": 0.0, "SurfFltRup": 0.0, "CountyName": "Santa Clara", "RailFlty_1": "CA000102", "TranspFclt": "RDFLT", "eqBldgType": "DFLT", "Tract_1": "06085503103", "Name": "SAN JOSE DISTRIBUTION SERVICES-SAN JOSE-", "Address": null, "City": "SAN JOSE", "Zipcode": "95112", "Statea": "CA", "FunctDay1": 77.1, "FunctDay3": 86.9, "FunctDay7": 90.3, "FunctDay14": 90.6, "FunctDay30": 91.6, "FunctDay90": 95.5, "PDsNone": 0.0691, "PDsSlight": 0.6099, "PDsModerat": 0.2051, "PDsExtensi": 0.0747, "PDsComplet": 0.0409, "PDsExceedS": 0.9308, "PDsExceedM": 0.3208, "PDsExceedE": 0.1156, "Latitude_1": 37.31019, "Longitude_": -121.86129, "CountyFips": "06085" }, "geometry": { "type": "Point", "coordinates": [ -121.861289999998917, 37.310190000000148 ] } },
{ "type": "Feature", "properties": { "RailFltyId": "CA000133", "Tract": "06001441503", "Longitude": -121.95111, "Latitude": 37.49733, "stype": null, "lqfsuscat": 4, "lndsuscat": 0, "w_depth": 0.0, "pgv": 24.0, "pga": 0.44, "sa03": 0.92, "sa10": 0.48, "LqfSettlPG": 0.0, "LqfSprPGD": 0.0, "LqfProb": 0.0, "LndPGD": 0.0, "LndProb": 0.0, "SufFltRupt": 0.0, "SurfFltRup": 0.0, "CountyName": "Alameda", "RailFlty_1": "CA000133", "TranspFclt": "RDFLT", "eqBldgType": "DFLT", "Tract_1": "06001441503", "Name": "TRUCK RAIL HANDLING\/QUALITY TRANSPORT IN", "Address": null, "City": "FREMONT", "Zipcode": "94538", "Statea": "CA", "FunctDay1": 54.5, "FunctDay3": 67.5, "FunctDay7": 72.2, "FunctDay14": 73.1, "FunctDay30": 75.3, "FunctDay90": 84.9, "PDsNone": 0.0155, "PDsSlight": 0.3859, "PDsModerat": 0.2706, "PDsExtensi": 0.1599, "PDsComplet": 0.1678, "PDsExceedS": 0.9844, "PDsExceedM": 0.5984, "PDsExceedE": 0.3278, "Latitude_1": 37.49733, "Longitude_": -121.95111, "CountyFips": "06001" }, "geometry": { "type": "Point", "coordinates": [ -121.95111, 37.497330000000147 ] } },
{ "type": "Feature", "properties": { "RailFltyId": "CA000197", "Tract": "06095252402", "Longitude": -122.0469, "Latitude": 38.236, "stype": null, "lqfsuscat": 5, "lndsuscat": 0, "w_depth": 0.0, "pgv": 4.0, "pga": 0.12, "sa03": 0.36, "sa10": 0.12, "LqfSettlPG": 0.0, "LqfSprPGD": 0.0, "LqfProb": 0.0, "LndPGD": 0.0, "LndProb": 0.0, "SufFltRupt": 0.0, "SurfFltRup": 0.0, "CountyName": "Solano", "RailFlty_1": "CA000197", "TranspFclt": "RDFLT", "eqBldgType": "DFLT", "Tract_1": "06095252402", "Name": "AMERICAN STITCHING AND BOX, INC.-FAIRFIE", "Address": null, "City": "FAIRFIELD", "Zipcode": "94533", "Statea": "CA", "FunctDay1": 97.1, "FunctDay3": 98.8, "FunctDay7": 99.4, "FunctDay14": 99.4, "FunctDay30": 99.5, "FunctDay90": 99.7, "PDsNone": 0.3971, "PDsSlight": 0.5596, "PDsModerat": 0.0368, "PDsExtensi": 0.0053, "PDsComplet": 0.001, "PDsExceedS": 0.6028, "PDsExceedM": 0.0432, "PDsExceedE": 0.0063, "Latitude_1": 38.236, "Longitude_": -122.0469, "CountyFips": "06095" }, "geometry": { "type": "Point", "coordinates": [ -122.046899999999368, 38.236000000000786 ] } },
{ "type": "Feature", "properties": { "RailFltyId": "CA000199", "Tract": "06013366002", "Longitude": -122.35534, "Latitude": 37.97193, "stype": null, "lqfsuscat": 3, "lndsuscat": 0, "w_depth": 0.0, "pgv": 52.0, "pga": 0.68, "sa03": 1.12, "sa10": 1.08, "LqfSettlPG": 0.0, "LqfSprPGD": 0.0, "LqfProb": 0.0, "LndPGD": 0.0, "LndProb": 0.0, "SufFltRupt": 0.0, "SurfFltRup": 0.0, "CountyName": "Contra Costa", "RailFlty_1": "CA000199", "TranspFclt": "RDFLT", "eqBldgType": "DFLT", "Tract_1": "06013366002", "Name": "WESTERN INTERMODAL SERVICES, LTD.-RICHMO", "Address": null, "City": "RICHMOND", "Zipcode": "94806", "Statea": "CA", "FunctDay1": 38.2, "FunctDay3": 51.5, "FunctDay7": 56.6, "FunctDay14": 57.9, "FunctDay30": 61.5, "FunctDay90": 76.8, "PDsNone": 0.003, "PDsSlight": 0.2081, "PDsModerat": 0.2751, "PDsExtensi": 0.2587, "PDsComplet": 0.2549, "PDsExceedS": 0.9969, "PDsExceedM": 0.7888, "PDsExceedE": 0.5137, "Latitude_1": 37.97193, "Longitude_": -122.35534, "CountyFips": "06013" }, "geometry": { "type": "Point", "coordinates": [ -122.35534, 37.971930000001521 ] } }
]
}
